ud2ude/__init__.py
ud2ude/api.py
ud2ude/conllu_wrapper.py
ud2ude/converter.py
ud2ude/graph_token.py
ud2ude/matcher.py
ud2ude/spacy_wrapper.py
ud2ude-2.2.2.dist-info/LICENSE
ud2ude-2.2.2.dist-info/METADATA
ud2ude-2.2.2.dist-info/WHEEL
ud2ude-2.2.2.dist-info/top_level.txt
ud2ude-2.2.2.dist-info/RECORD
