Metadata-Version: 2.1
Name: ud2ude
Version: 2.2.2
Summary: python converter from UD to enhanced UD representations
Home-page: https://github.com/allenai/UD2UDE
Author: Aryeh Tiktinsky
Author-email: aryehgigi@gmail.com
License: UNKNOWN
Platform: UNKNOWN
Classifier: Programming Language :: Python :: 3.7
Classifier: License :: OSI Approved :: Apache Software License
Classifier: Operating System :: OS Independent
Requires-Python: >=3.7
